m9ini/__init__.py
m9ini/u_config.py
m9ini/u_config_base.py
m9ini/u_config_lock.py
m9ini/u_config_parameters.py
m9ini/u_config_section.py
m9ini/u_config_utils.py
m9ini-1.0.4.dist-info/licenses/LICENSE
m9ini-1.0.4.dist-info/METADATA
m9ini-1.0.4.dist-info/WHEEL
m9ini-1.0.4.dist-info/top_level.txt
m9ini-1.0.4.dist-info/RECORD
