Metadata-Version: 2.4
Name: m9ini
Version: 1.0.4
Summary: m9 ini configuration
Author: M. Fairbanks
Author-email: marcusnyne@gmail.com
License-Expression: Apache-2.0
Project-URL: Homepage, https://github.com/MarcusNyne/m9ini
Keywords: INI,configuration,config,settings,parse,load,batch
Classifier: Programming Language :: Python :: 3
Classifier: Operating System :: OS Independent
Requires-Python: >=3.10.6
License-File: LICENSE
Provides-Extra: dev
Dynamic: license-file
